data_analysis_framework/__init__.py
data_analysis_framework/unified_interface.py
data_analysis_framework/core/__init__.py
data_analysis_framework/core/agent_interface.py
data_analysis_framework/core/analyzer.py
data_analysis_framework/core/profiler.py
data_analysis_framework/handlers/__init__.py
data_analysis_framework/utils/__init__.py
data_analysis_framework-1.1.0.dist-info/licenses/LICENSE
data_analysis_framework-1.1.0.dist-info/METADATA
data_analysis_framework-1.1.0.dist-info/WHEEL
data_analysis_framework-1.1.0.dist-info/entry_points.txt
data_analysis_framework-1.1.0.dist-info/top_level.txt
data_analysis_framework-1.1.0.dist-info/RECORD
